swagger_zipkin/__init__.py
swagger_zipkin/decorate_client.py
swagger_zipkin/zipkin_decorator.py
swagger_zipkin-0.5.1.dist-info/LICENSE.txt
swagger_zipkin-0.5.1.dist-info/METADATA
swagger_zipkin-0.5.1.dist-info/WHEEL
swagger_zipkin-0.5.1.dist-info/top_level.txt
swagger_zipkin-0.5.1.dist-info/RECORD
