Metadata-Version: 2.1
Name: swagger-zipkin
Version: 0.5.1
Summary: Zipkin decorators for swagger clients - swagger-py and bravado.
Home-page: https://github.com/Yelp/swagger_zipkin
Author: Yelp, Inc.
Author-email: opensource+swagger-zipkin@yelp.com
License: Copyright Yelp 2016
Keywords: zipkin
Platform: UNKNOWN
Classifier: Development Status :: 5 - Production/Stable
Classifier: Intended Audience :: Developers
Classifier: Topic :: Software Development :: Libraries :: Python Modules
Classifier: License :: OSI Approved :: Apache Software License
Classifier: Operating System :: OS Independent
Classifier: Programming Language :: Python :: 3
Classifier: Programming Language :: Python :: 3.7
Classifier: Programming Language :: Python :: 3.8
Provides: swagger_zipkin
Requires-Python: >=3.7
Requires-Dist: py-zipkin (>=0.10.1)
